<?xml version="1.0" encoding="UTF-8" ?>
<!DOCTYPE tiles-definitions PUBLIC
        "-//Apache Software Foundation//DTD Tiles Configuration 3.0//EN"
        "http://tiles.apache.org/dtds/tiles-config_3_0.dtd">

<tiles-definitions>
     <definition name="base.defination" template="/WEB-INF/pages/tiles/layout.jsp">
         <put-attribute name="title" value=""/>
         <put-attribute name="header" value="/WEB-INF/pages/tiles/header.jsp"/>
         <put-attribute name="menu" value="/WEB-INF/pages/tiles/menu.jsp"/>
         <put-attribute name="body" value=""/>
         <put-attribute name="footer" value="/WEB-INF/pages/tiles/footer.jsp" />
     </definition>

     <definition name="student-login" extends="base.defination">
         <put-attribute name="title" value="student login"/>
         <put-attribute name="body" value="/WEB-INF/pages/student-login.jsp"/>
     </definition>

    <definition name="enroll-student" extends="base.defination">
        <put-attribute name="title" value="enroll login"/>
        <put-attribute name="body" value="/WEB-INF/pages/enroll-student.jsp"/>
    </definition>

    <definition name="enroll-details" extends="base.defination">
        <put-attribute name="title" value="success page"/>
        <put-attribute name="body" value="/WEB-INF/pages/enroll-list.jsp"/>
    </definition>

    <definition name="edit-form" extends="base.defination">
        <put-attribute name="title" value="success page"/>
        <put-attribute name="body" value="/WEB-INF/pages/edit-form.jsp"/>
    </definition>

    <definition name="success" extends="base.defination">
        <put-attribute name="title" value="success page"/>
        <put-attribute name="body" value="/WEB-INF/pages/result/success.jsp"/>
    </definition>

</tiles-definitions>
